echelon/__init__.py
echelon/oracle.py
echelon/scan_oracle.py
echelon/test.py
echelon/typing.py
echelon/algorithms/__init__.py
echelon/algorithms/find_echelon_clusters.py
echelon/algorithms/find_echelon_hierarchy.py
echelon/algorithms/find_echelon_hotspots.py
echelon/algorithms/find_foundation_echelons.py
echelon/algorithms/find_peak_echelons.py
echelon/algorithms/util.py
echelon/api/__init__.py
echelon/api/base.py
echelon/api/dataframe_api.py
echelon/api/ndarray_api.py
echelon/contrib/__init__.py
echelon/contrib/geo.py
echelon_py-1.1.0.dist-info/LICENSE
echelon_py-1.1.0.dist-info/METADATA
echelon_py-1.1.0.dist-info/WHEEL
echelon_py-1.1.0.dist-info/top_level.txt
echelon_py-1.1.0.dist-info/RECORD
